<?xml version="1.0"?>
<!--
 SPDX-License-Identifier: LGPL-2.1-or-later
 SPDX-FileCopyrightText: Copyright © the xdg-desktop-portal contributors
-->

<node name="/" xmlns:doc="http://www.freedesktop.org/dbus/1.0/doc.dtd">
    <!--
      org.freedesktop.portal.Realtime:
      @short_description: Portal for setting threads to realtime

      Interface for setting a thread to realtime from within the
      sandbox. It is analogous to the org.freedesktop.RealtimeKit1
      interface and will proxy requests there but with pid mapping.
      The latter is necessary in the case that sandbox has pid namespace
      isolation enabled.

      Note that this proxy does not bypass any limitations that
      RealtimeKit imposes on processes which are documented here:
      https://git.0pointer.net/rtkit.git/tree/README

      This documentation describes version 1 of this interface.
    -->
    <interface name="org.freedesktop.portal.Realtime">
      <!--
          MakeThreadRealtimeWithPID:
          @process: Process id
          @thread: Thread id
          @priority: Priority
      -->
      <method name="MakeThreadRealtimeWithPID">
        <arg type="t" name="process" direction="in"/>
        <arg type="t" name="thread" direction="in"/>
        <arg type="u" name="priority" direction="in"/>
      </method>

      <!--
          MakeThreadHighPriorityWithPID:
          @process: Process id
          @thread: Thread id
          @priority: Priority
      -->
      <method name="MakeThreadHighPriorityWithPID">
        <arg type="t" name="process" direction="in"/>
        <arg type="t" name="thread" direction="in"/>
        <arg type="i" name="priority" direction="in"/>
      </method>

      <property name="MaxRealtimePriority" type="i" access="read"/>
      <property name="MinNiceLevel" type="i" access="read"/>
      <property name="RTTimeUSecMax" type="x" access="read"/>

      <property name="version" type="u" access="read"/>
    </interface>
</node>
